webgym/__init__.py
webgym/agent.py
webgym/env.py
webgym/spaces.py
webgym/types.py
webgymnasium-0.0.0.dist-info/LICENSE
webgymnasium-0.0.0.dist-info/METADATA
webgymnasium-0.0.0.dist-info/WHEEL
webgymnasium-0.0.0.dist-info/top_level.txt
webgymnasium-0.0.0.dist-info/RECORD
