Metadata-Version: 2.1
Name: webgymnasium
Version: 0.0.0
Summary: A set of RL environments for training LMs on the live web.
Author-email: Niels Bantilan <niels.bantilan@gmail.com>
License: Apache License
Project-URL: Homepage, https://github.com/hai-labs/webgymnasium
Classifier: Intended Audience :: Science/Research
Classifier: Intended Audience :: Developers
Classifier: License :: Other/Proprietary License
Classifier: Programming Language :: Python :: 3.8
Classifier: Programming Language :: Python :: 3.9
Classifier: Programming Language :: Python :: 3.10
Classifier: Programming Language :: Python :: 3.11
Classifier: Programming Language :: Python :: 3.12
Classifier: Topic :: Scientific/Engineering
Classifier: Topic :: Scientific/Engineering :: Artificial Intelligence
Classifier: Topic :: Software Development
Classifier: Topic :: Software Development :: Libraries
Classifier: Topic :: Software Development :: Libraries :: Python Modules
Requires-Python: >=3.8
License-File: LICENSE
Requires-Dist: html2text
Requires-Dist: httpx
Requires-Dist: gymnasium
Requires-Dist: markdownify
Requires-Dist: ollama
Requires-Dist: pydantic
Requires-Dist: pygame
